{"page":155,"juz":8,"surahs":[7],"lines":[{"n":1,"words":[{"g":"пұҒ","v":"7:38","e":0},{"g":"пұӮ","v":"7:38","e":0},{"g":"пұғ","v":"7:38","e":0},{"g":"пұ„","v":"7:38","e":0},{"g":"пұ…","v":"7:38","e":0},{"g":"пұҶ","v":"7:38","e":0},{"g":"пұҮ","v":"7:38","e":0},{"g":"пұҲ","v":"7:38","e":0},{"g":"пұү","v":"7:38","e":0},{"g":"пұҠ","v":"7:38","e":0},{"g":"пұӢ","v":"7:38","e":0}]},{"n":2,"words":[{"g":"пұҢ","v":"7:38","e":0},{"g":"пұҚпұҺ","v":"7:38","e":0},{"g":"пұҸ","v":"7:38","e":0},{"g":"пұҗ","v":"7:38","e":0},{"g":"пұ‘","v":"7:38","e":0},{"g":"пұ’","v":"7:38","e":0},{"g":"пұ“пұ”","v":"7:38","e":0},{"g":"пұ•","v":"7:38","e":0},{"g":"пұ–","v":"7:38","e":0},{"g":"пұ—","v":"7:38","e":0}]},{"n":3,"words":[{"g":"пұҳ","v":"7:38","e":0},{"g":"пұҷ","v":"7:38","e":0},{"g":"пұҡ","v":"7:38","e":0},{"g":"пұӣ","v":"7:38","e":0},{"g":"пұң","v":"7:38","e":0},{"g":"пұқ","v":"7:38","e":0},{"g":"пұһ","v":"7:38","e":0},{"g":"пұҹ","v":"7:38","e":0},{"g":"пұ ","v":"7:38","e":0}]},{"n":4,"words":[{"g":"пұЎ","v":"7:38","e":0},{"g":"пұў","v":"7:38","e":0},{"g":"пұЈ","v":"7:38","e":0},{"g":"пұӨпұҘ","v":"7:38","e":0},{"g":"пұҰ","v":"7:38","e":0},{"g":"пұ§","v":"7:38","e":0},{"g":"пұЁ","v":"7:38","e":0},{"g":"пұ©","v":"7:38","e":0},{"g":"пұӘ","v":"7:38","e":0},{"g":"пұ«","v":"7:38","e":0}]},{"n":5,"words":[{"g":"пұ¬","v":"7:38","e":1},{"g":"пұӯ","v":"7:39","e":0},{"g":"пұ®","v":"7:39","e":0},{"g":"пұҜ","v":"7:39","e":0},{"g":"пұ°","v":"7:39","e":0},{"g":"пұұ","v":"7:39","e":0},{"g":"пұІ","v":"7:39","e":0},{"g":"пұі","v":"7:39","e":0},{"g":"пұҙ","v":"7:39","e":0},{"g":"пұө","v":"7:39","e":0}]},{"n":6,"words":[{"g":"пұ¶","v":"7:39","e":0},{"g":"пұ·","v":"7:39","e":0},{"g":"пұё","v":"7:39","e":0},{"g":"пұ№","v":"7:39","e":0},{"g":"пұә","v":"7:39","e":0},{"g":"пұ»","v":"7:39","e":1},{"g":"пұј","v":"7:40","e":0},{"g":"пұҪ","v":"7:40","e":0}]},{"n":7,"words":[{"g":"пұҫ","v":"7:40","e":0},{"g":"пұҝ","v":"7:40","e":0},{"g":"пІҖ","v":"7:40","e":0},{"g":"пІҒ","v":"7:40","e":0},{"g":"пІӮ","v":"7:40","e":0},{"g":"пІғ","v":"7:40","e":0},{"g":"пІ„","v":"7:40","e":0},{"g":"пІ…","v":"7:40","e":0},{"g":"пІҶ","v":"7:40","e":0}]},{"n":8,"words":[{"g":"пІҮ","v":"7:40","e":0},{"g":"пІҲ","v":"7:40","e":0},{"g":"пІү","v":"7:40","e":0},{"g":"пІҠ","v":"7:40","e":0},{"g":"пІӢ","v":"7:40","e":0},{"g":"пІҢ","v":"7:40","e":0},{"g":"пІҚ","v":"7:40","e":0},{"g":"пІҺ","v":"7:40","e":0},{"g":"пІҸпІҗ","v":"7:40","e":0},{"g":"пІ‘","v":"7:40","e":0}]},{"n":9,"words":[{"g":"пІ’","v":"7:40","e":0},{"g":"пІ“","v":"7:40","e":0},{"g":"пІ”","v":"7:40","e":1},{"g":"пІ•","v":"7:41","e":0},{"g":"пІ–","v":"7:41","e":0},{"g":"пІ—","v":"7:41","e":0},{"g":"пІҳ","v":"7:41","e":0},{"g":"пІҷ","v":"7:41","e":0},{"g":"пІҡ","v":"7:41","e":0},{"g":"пІӣпІң","v":"7:41","e":0}]},{"n":10,"words":[{"g":"пІқ","v":"7:41","e":0},{"g":"пІһ","v":"7:41","e":0},{"g":"пІҹ","v":"7:41","e":0},{"g":"пІ ","v":"7:41","e":1},{"g":"пІЎ","v":"7:42","e":0},{"g":"пІў","v":"7:42","e":0},{"g":"пІЈ","v":"7:42","e":0},{"g":"пІӨ","v":"7:42","e":0}]},{"n":11,"words":[{"g":"пІҘ","v":"7:42","e":0},{"g":"пІҰ","v":"7:42","e":0},{"g":"пІ§","v":"7:42","e":0},{"g":"пІЁ","v":"7:42","e":0},{"g":"пІ©","v":"7:42","e":0},{"g":"пІӘ","v":"7:42","e":0},{"g":"пІ«","v":"7:42","e":0},{"g":"пІ¬пІӯ","v":"7:42","e":0},{"g":"пІ®","v":"7:42","e":0}]},{"n":12,"words":[{"g":"пІҜ","v":"7:42","e":0},{"g":"пІ°","v":"7:42","e":0},{"g":"пІұ","v":"7:42","e":1},{"g":"пІІ","v":"7:43","e":0},{"g":"пІі","v":"7:43","e":0},{"g":"пІҙ","v":"7:43","e":0},{"g":"пІө","v":"7:43","e":0},{"g":"пІ¶","v":"7:43","e":0},{"g":"пІ·","v":"7:43","e":0},{"g":"пІё","v":"7:43","e":0}]},{"n":13,"words":[{"g":"пІ№","v":"7:43","e":0},{"g":"пІә","v":"7:43","e":0},{"g":"пІ»пІј","v":"7:43","e":0},{"g":"пІҪ","v":"7:43","e":0},{"g":"пІҫ","v":"7:43","e":0},{"g":"пІҝ","v":"7:43","e":0},{"g":"піҖ","v":"7:43","e":0},{"g":"піҒ","v":"7:43","e":0},{"g":"піӮ","v":"7:43","e":0},{"g":"піғ","v":"7:43","e":0},{"g":"пі„","v":"7:43","e":0}]},{"n":14,"words":[{"g":"пі…","v":"7:43","e":0},{"g":"піҶ","v":"7:43","e":0},{"g":"піҮ","v":"7:43","e":0},{"g":"піҲ","v":"7:43","e":0},{"g":"піүпіҠ","v":"7:43","e":0},{"g":"піӢ","v":"7:43","e":0},{"g":"піҢ","v":"7:43","e":0},{"g":"піҚ","v":"7:43","e":0},{"g":"піҺ","v":"7:43","e":0},{"g":"піҸпіҗ","v":"7:43","e":0}]},{"n":15,"words":[{"g":"пі‘","v":"7:43","e":0},{"g":"пі’","v":"7:43","e":0},{"g":"пі“","v":"7:43","e":0},{"g":"пі”","v":"7:43","e":0},{"g":"пі•","v":"7:43","e":0},{"g":"пі–","v":"7:43","e":0},{"g":"пі—","v":"7:43","e":0},{"g":"піҳ","v":"7:43","e":0},{"g":"піҷ","v":"7:43","e":1}]}]}