{"page":499,"juz":25,"surahs":[45],"lines":[{"n":2,"words":[{"g":"’▒ü","v":"45:1","e":0},{"g":"’▒é","v":"45:1","e":1},{"g":"’▒ā","v":"45:2","e":0},{"g":"’▒ä","v":"45:2","e":0},{"g":"’▒ģ","v":"45:2","e":0},{"g":"’▒å","v":"45:2","e":0},{"g":"’▒ć","v":"45:2","e":0},{"g":"’▒ł","v":"45:2","e":0},{"g":"’▒ē","v":"45:2","e":1},{"g":"’▒Ŗ","v":"45:3","e":0},{"g":"’▒ŗ","v":"45:3","e":0},{"g":"’▒ī","v":"45:3","e":0}]},{"n":3,"words":[{"g":"’▒Ź","v":"45:3","e":0},{"g":"’▒Ä","v":"45:3","e":0},{"g":"’▒Å","v":"45:3","e":0},{"g":"’▒É","v":"45:3","e":1},{"g":"’▒æ","v":"45:4","e":0},{"g":"’▒Æ","v":"45:4","e":0},{"g":"’▒ō","v":"45:4","e":0},{"g":"’▒ö","v":"45:4","e":0},{"g":"’▒Ģ","v":"45:4","e":0},{"g":"’▒¢","v":"45:4","e":0},{"g":"’▒Ś","v":"45:4","e":0}]},{"n":4,"words":[{"g":"’▒ś","v":"45:4","e":0},{"g":"’▒Ö","v":"45:4","e":0},{"g":"’▒Ü","v":"45:4","e":1},{"g":"’▒ø","v":"45:5","e":0},{"g":"’▒£","v":"45:5","e":0},{"g":"’▒Ø","v":"45:5","e":0},{"g":"’▒×","v":"45:5","e":0},{"g":"’▒¤","v":"45:5","e":0},{"g":"’▒Ā","v":"45:5","e":0},{"g":"’▒Ī","v":"45:5","e":0},{"g":"’▒ó","v":"45:5","e":0}]},{"n":5,"words":[{"g":"’▒Ż","v":"45:5","e":0},{"g":"’▒ż","v":"45:5","e":0},{"g":"’▒ź","v":"45:5","e":0},{"g":"’▒”","v":"45:5","e":0},{"g":"’▒¦","v":"45:5","e":0},{"g":"’▒©","v":"45:5","e":0},{"g":"’▒®","v":"45:5","e":0},{"g":"’▒¬","v":"45:5","e":0},{"g":"’▒½","v":"45:5","e":0},{"g":"’▒¼","v":"45:5","e":0},{"g":"’▒Ł","v":"45:5","e":0}]},{"n":6,"words":[{"g":"’▒«","v":"45:5","e":0},{"g":"’▒»","v":"45:5","e":1},{"g":"’▒░","v":"45:6","e":0},{"g":"’▒▒","v":"45:6","e":0},{"g":"’▒▓","v":"45:6","e":0},{"g":"’▒│","v":"45:6","e":0},{"g":"’▒┤","v":"45:6","e":0},{"g":"’▒Ą’▒Č","v":"45:6","e":0},{"g":"’▒Ę","v":"45:6","e":0},{"g":"’▒Ė","v":"45:6","e":0},{"g":"’▒╣","v":"45:6","e":0}]},{"n":7,"words":[{"g":"’▒║","v":"45:6","e":0},{"g":"’▒╗","v":"45:6","e":0},{"g":"’▒╝","v":"45:6","e":0},{"g":"’▒Į","v":"45:6","e":1},{"g":"’▒Š","v":"45:7","e":0},{"g":"’▒┐","v":"45:7","e":0},{"g":"’▓Ć","v":"45:7","e":0},{"g":"’▓ü","v":"45:7","e":0},{"g":"’▓é","v":"45:7","e":1},{"g":"’▓ā","v":"45:8","e":0},{"g":"’▓ä","v":"45:8","e":0}]},{"n":8,"words":[{"g":"’▓ģ","v":"45:8","e":0},{"g":"’▓å","v":"45:8","e":0},{"g":"’▓ć","v":"45:8","e":0},{"g":"’▓ł","v":"45:8","e":0},{"g":"’▓ē","v":"45:8","e":0},{"g":"’▓Ŗ","v":"45:8","e":0},{"g":"’▓ŗ","v":"45:8","e":0},{"g":"’▓ī","v":"45:8","e":0},{"g":"’▓Ź’▓Ä","v":"45:8","e":0},{"g":"’▓Å","v":"45:8","e":0},{"g":"’▓É","v":"45:8","e":0},{"g":"’▓æ","v":"45:8","e":0}]},{"n":9,"words":[{"g":"’▓Æ","v":"45:8","e":1},{"g":"’▓ō","v":"45:9","e":0},{"g":"’▓ö","v":"45:9","e":0},{"g":"’▓Ģ","v":"45:9","e":0},{"g":"’▓¢","v":"45:9","e":0},{"g":"’▓Ś","v":"45:9","e":0},{"g":"’▓ś","v":"45:9","e":0},{"g":"’▓Ö’▓Ü","v":"45:9","e":0},{"g":"’▓ø","v":"45:9","e":0},{"g":"’▓£","v":"45:9","e":0},{"g":"’▓Ø","v":"45:9","e":0}]},{"n":10,"words":[{"g":"’▓×","v":"45:9","e":0},{"g":"’▓¤","v":"45:9","e":1},{"g":"’▓Ā","v":"45:10","e":0},{"g":"’▓Ī","v":"45:10","e":0},{"g":"’▓ó’▓Ż","v":"45:10","e":0},{"g":"’▓ż","v":"45:10","e":0},{"g":"’▓ź","v":"45:10","e":0},{"g":"’▓”","v":"45:10","e":0},{"g":"’▓¦","v":"45:10","e":0},{"g":"’▓©","v":"45:10","e":0},{"g":"’▓®","v":"45:10","e":0}]},{"n":11,"words":[{"g":"’▓¬","v":"45:10","e":0},{"g":"’▓½","v":"45:10","e":0},{"g":"’▓¼","v":"45:10","e":0},{"g":"’▓Ł","v":"45:10","e":0},{"g":"’▓«","v":"45:10","e":0},{"g":"’▓»","v":"45:10","e":0},{"g":"’▓░’▓▒","v":"45:10","e":0},{"g":"’▓▓","v":"45:10","e":0},{"g":"’▓│","v":"45:10","e":0},{"g":"’▓┤","v":"45:10","e":0},{"g":"’▓Ą","v":"45:10","e":1},{"g":"’▓Č","v":"45:11","e":0}]},{"n":12,"words":[{"g":"’▓Ę’▓Ė","v":"45:11","e":0},{"g":"’▓╣","v":"45:11","e":0},{"g":"’▓║","v":"45:11","e":0},{"g":"’▓╗","v":"45:11","e":0},{"g":"’▓╝","v":"45:11","e":0},{"g":"’▓Į","v":"45:11","e":0},{"g":"’▓Š","v":"45:11","e":0},{"g":"’▓┐","v":"45:11","e":0},{"g":"’│Ć","v":"45:11","e":0},{"g":"’│ü","v":"45:11","e":0},{"g":"’│é","v":"45:11","e":1}]},{"n":13,"words":[{"g":"’│ā ’│ä","v":"45:12","e":0},{"g":"’│ģ","v":"45:12","e":0},{"g":"’│å","v":"45:12","e":0},{"g":"’│ć","v":"45:12","e":0},{"g":"’│ł","v":"45:12","e":0},{"g":"’│ē","v":"45:12","e":0},{"g":"’│Ŗ","v":"45:12","e":0},{"g":"’│ŗ","v":"45:12","e":0},{"g":"’│ī","v":"45:12","e":0},{"g":"’│Ź","v":"45:12","e":0}]},{"n":14,"words":[{"g":"’│Ä","v":"45:12","e":0},{"g":"’│Å","v":"45:12","e":0},{"g":"’│É","v":"45:12","e":0},{"g":"’│æ","v":"45:12","e":0},{"g":"’│Æ","v":"45:12","e":1},{"g":"’│ō","v":"45:13","e":0},{"g":"’│ö","v":"45:13","e":0},{"g":"’│Ģ","v":"45:13","e":0},{"g":"’│¢","v":"45:13","e":0},{"g":"’│Ś","v":"45:13","e":0},{"g":"’│ś","v":"45:13","e":0},{"g":"’│Ö","v":"45:13","e":0}]},{"n":15,"words":[{"g":"’│Ü","v":"45:13","e":0},{"g":"’│ø","v":"45:13","e":0},{"g":"’│£’│Ø","v":"45:13","e":0},{"g":"’│×","v":"45:13","e":0},{"g":"’│¤","v":"45:13","e":0},{"g":"’│Ā","v":"45:13","e":0},{"g":"’│Ī","v":"45:13","e":0},{"g":"’│ó","v":"45:13","e":0},{"g":"’│Ż","v":"45:13","e":0},{"g":"’│ż","v":"45:13","e":1}]}]}