{"page":515,"juz":26,"surahs":[48,49],"lines":[{"n":1,"words":[{"g":"’▒ü","v":"48:29","e":0},{"g":"’▒é","v":"48:29","e":0},{"g":"’▒ā’▒ä","v":"48:29","e":0},{"g":"’▒ģ","v":"48:29","e":0},{"g":"’▒å","v":"48:29","e":0},{"g":"’▒ć","v":"48:29","e":0},{"g":"’▒ł","v":"48:29","e":0},{"g":"’▒ē","v":"48:29","e":0},{"g":"’▒Ŗ","v":"48:29","e":0},{"g":"’▒ŗ’▒ī","v":"48:29","e":0}]},{"n":2,"words":[{"g":"’▒Ź","v":"48:29","e":0},{"g":"’▒Ä","v":"48:29","e":0},{"g":"’▒Å","v":"48:29","e":0},{"g":"’▒É","v":"48:29","e":0},{"g":"’▒æ","v":"48:29","e":0},{"g":"’▒Æ","v":"48:29","e":0},{"g":"’▒ō","v":"48:29","e":0},{"g":"’▒ö’▒Ģ","v":"48:29","e":0},{"g":"’▒¢","v":"48:29","e":0}]},{"n":3,"words":[{"g":"’▒Ś","v":"48:29","e":0},{"g":"’▒ś","v":"48:29","e":0},{"g":"’▒Ö","v":"48:29","e":0},{"g":"’▒Ü","v":"48:29","e":0},{"g":"’▒ø’▒£","v":"48:29","e":0},{"g":"’▒Ø","v":"48:29","e":0},{"g":"’▒×","v":"48:29","e":0},{"g":"’▒¤","v":"48:29","e":0},{"g":"’▒Ā’▒Ī","v":"48:29","e":0},{"g":"’▒ó","v":"48:29","e":0},{"g":"’▒Ż","v":"48:29","e":0}]},{"n":4,"words":[{"g":"’▒ż","v":"48:29","e":0},{"g":"’▒ź","v":"48:29","e":0},{"g":"’▒”","v":"48:29","e":0},{"g":"’▒¦","v":"48:29","e":0},{"g":"’▒©","v":"48:29","e":0},{"g":"’▒®","v":"48:29","e":0},{"g":"’▒¬","v":"48:29","e":0}]},{"n":5,"words":[{"g":"’▒½","v":"48:29","e":0},{"g":"’▒¼","v":"48:29","e":0},{"g":"’▒Ł","v":"48:29","e":0},{"g":"’▒«","v":"48:29","e":0},{"g":"’▒»","v":"48:29","e":0},{"g":"’▒░","v":"48:29","e":0},{"g":"’▒▒’▒▓","v":"48:29","e":0},{"g":"’▒│","v":"48:29","e":0},{"g":"’▒┤","v":"48:29","e":0},{"g":"’▒Ą","v":"48:29","e":0}]},{"n":6,"words":[{"g":"’▒Č","v":"48:29","e":0},{"g":"’▒Ę","v":"48:29","e":0},{"g":"’▒Ė","v":"48:29","e":0},{"g":"’▒╣","v":"48:29","e":0},{"g":"’▒║","v":"48:29","e":0},{"g":"’▒╗","v":"48:29","e":0},{"g":"’▒╝","v":"48:29","e":0},{"g":"’▒Į","v":"48:29","e":1}]},{"n":9,"words":[{"g":"’▒Š","v":"49:1","e":0},{"g":"’▒┐","v":"49:1","e":0},{"g":"’▓Ć","v":"49:1","e":0},{"g":"’▓ü","v":"49:1","e":0},{"g":"’▓é","v":"49:1","e":0},{"g":"’▓ā","v":"49:1","e":0},{"g":"’▓ä","v":"49:1","e":0},{"g":"’▓ģ","v":"49:1","e":0},{"g":"’▓å’▓ć","v":"49:1","e":0},{"g":"’▓ł","v":"49:1","e":0}]},{"n":10,"words":[{"g":"’▓ē’▓Ŗ","v":"49:1","e":0},{"g":"’▓ŗ","v":"49:1","e":0},{"g":"’▓ī","v":"49:1","e":0},{"g":"’▓Ź","v":"49:1","e":0},{"g":"’▓Ä","v":"49:1","e":0},{"g":"’▓Å","v":"49:1","e":1},{"g":"’▓É","v":"49:2","e":0},{"g":"’▓æ","v":"49:2","e":0},{"g":"’▓Æ","v":"49:2","e":0},{"g":"’▓ō","v":"49:2","e":0},{"g":"’▓ö","v":"49:2","e":0}]},{"n":11,"words":[{"g":"’▓Ģ","v":"49:2","e":0},{"g":"’▓¢","v":"49:2","e":0},{"g":"’▓Ś","v":"49:2","e":0},{"g":"’▓ś","v":"49:2","e":0},{"g":"’▓Ö","v":"49:2","e":0},{"g":"’▓Ü","v":"49:2","e":0},{"g":"’▓ø","v":"49:2","e":0},{"g":"’▓£","v":"49:2","e":0},{"g":"’▓Ø","v":"49:2","e":0},{"g":"’▓×","v":"49:2","e":0}]},{"n":12,"words":[{"g":"’▓¤","v":"49:2","e":0},{"g":"’▓Ā","v":"49:2","e":0},{"g":"’▓Ī","v":"49:2","e":0},{"g":"’▓ó","v":"49:2","e":0},{"g":"’▓Ż","v":"49:2","e":0},{"g":"’▓ż","v":"49:2","e":0},{"g":"’▓ź","v":"49:2","e":0},{"g":"’▓”","v":"49:2","e":1},{"g":"’▓¦","v":"49:3","e":0},{"g":"’▓©","v":"49:3","e":0}]},{"n":13,"words":[{"g":"’▓®","v":"49:3","e":0},{"g":"’▓¬","v":"49:3","e":0},{"g":"’▓½","v":"49:3","e":0},{"g":"’▓¼","v":"49:3","e":0},{"g":"’▓Ł","v":"49:3","e":0},{"g":"’▓«","v":"49:3","e":0},{"g":"’▓»","v":"49:3","e":0},{"g":"’▓░","v":"49:3","e":0}]},{"n":14,"words":[{"g":"’▓▒","v":"49:3","e":0},{"g":"’▓▓","v":"49:3","e":0},{"g":"’▓│’▓┤","v":"49:3","e":0},{"g":"’▓Ą","v":"49:3","e":0},{"g":"’▓Č","v":"49:3","e":0},{"g":"’▓Ę","v":"49:3","e":0},{"g":"’▓Ė","v":"49:3","e":0},{"g":"’▓╣","v":"49:3","e":1},{"g":"’▓║","v":"49:4","e":0},{"g":"’▓╗","v":"49:4","e":0}]},{"n":15,"words":[{"g":"’▓╝","v":"49:4","e":0},{"g":"’▓Į","v":"49:4","e":0},{"g":"’▓Š","v":"49:4","e":0},{"g":"’▓┐","v":"49:4","e":0},{"g":"’│Ć","v":"49:4","e":0},{"g":"’│ü","v":"49:4","e":0},{"g":"’│é","v":"49:4","e":0},{"g":"’│ā","v":"49:4","e":1}]}]}